django_presigned_url/__init__.py
django_presigned_url/presign_urls.py
django_presigned_url-0.1.1.dist-info/LICENSE
django_presigned_url-0.1.1.dist-info/METADATA
django_presigned_url-0.1.1.dist-info/WHEEL
django_presigned_url-0.1.1.dist-info/RECORD
